scrapyd_kit/__init__.py
scrapyd_kit/services/__init__.py
scrapyd_kit/services/crawl.py
scrapyd_kit-0.1.6.dist-info/DESCRIPTION.rst
scrapyd_kit-0.1.6.dist-info/METADATA
scrapyd_kit-0.1.6.dist-info/RECORD
scrapyd_kit-0.1.6.dist-info/WHEEL
scrapyd_kit-0.1.6.dist-info/metadata.json
scrapyd_kit-0.1.6.dist-info/top_level.txt
