Metadata-Version: 2.0
Name: scrapyd-kit
Version: 0.1.6
Summary: A kit for extending Scrapyd
Home-page: https://github.com/soasme/scrapyd_kit
Author: Lin Ju
Author-email: soasme@gmail.com
License: BSD
Platform: UNKNOWN
Classifier: Programming Language :: Python
Classifier: Programming Language :: Python :: 2.6
Classifier: Programming Language :: Python :: 2.7
Classifier: License :: OSI Approved :: BSD License
Classifier: Operating System :: OS Independent
Classifier: Development Status :: 5 - Production/Stable
Classifier: Environment :: Console
Classifier: Environment :: No Input/Output (Daemon)
Classifier: Topic :: Internet :: WWW/HTTP
Requires-Dist: Scrapy (>=0.17)
Requires-Dist: Twisted (>=8.0)
